raster_tools/__init__.py
raster_tools/_compat.py
raster_tools/_version.py
raster_tools/batch.py
raster_tools/clipping.py
raster_tools/creation.py
raster_tools/dask_utils.py
raster_tools/dtypes.py
raster_tools/exceptions.py
raster_tools/focal.py
raster_tools/general.py
raster_tools/io.py
raster_tools/line_stats.py
raster_tools/masking.py
raster_tools/raster.py
raster_tools/rasterize.py
raster_tools/stat_common.py
raster_tools/surface.py
raster_tools/utils.py
raster_tools/vector.py
raster_tools/warp.py
raster_tools/zonal.py
raster_tools/distance/__init__.py
raster_tools/distance/_heap.py
raster_tools/distance/cost_distance.py
raster_tools/distance/proximity.py
raster_tools-0.9.10.dist-info/licenses/LICENSE
raster_tools-0.9.10.dist-info/METADATA
raster_tools-0.9.10.dist-info/WHEEL
raster_tools-0.9.10.dist-info/top_level.txt
raster_tools-0.9.10.dist-info/RECORD
