Metadata-Version: 2.4
Name: raster-tools
Version: 0.9.10
Summary: Tools for processing geospatial data
Home-page: https://github.com/UM-RMRS/raster_tools
License: GPL-3.0
Project-URL: Bug Tracker, https://github.com/UM-RMRS/raster_tools/issues
Classifier: Intended Audience :: Science/Research
Classifier: License :: OSI Approved :: GNU General Public License v3 (GPLv3)
Classifier: Operating System :: OS Independent
Classifier: Programming Language :: Python :: 3
Classifier: Topic :: Scientific/Engineering :: GIS
Requires-Python: >=3.9
License-File: LICENSE
Requires-Dist: affine
Requires-Dist: cfgrib
Requires-Dist: dask
Requires-Dist: dask-geopandas
Requires-Dist: dask-image
Requires-Dist: fiona
Requires-Dist: geopandas
Requires-Dist: netcdf4
Requires-Dist: numba
Requires-Dist: numpy>=1.22
Requires-Dist: odc-geo<=0.4.11
Requires-Dist: pandas
Requires-Dist: pyogrio
Requires-Dist: pyproj
Requires-Dist: rioxarray
Requires-Dist: rasterio
Requires-Dist: scipy
Requires-Dist: shapely>=2.0
Requires-Dist: xarray
Dynamic: classifier
Dynamic: description
Dynamic: description-content-type
Dynamic: home-page
Dynamic: license
Dynamic: license-file
Dynamic: project-url
Dynamic: requires-dist
Dynamic: requires-python
Dynamic: summary
